hiveengine/__init__.py
hiveengine/api.py
hiveengine/cli.py
hiveengine/collection.py
hiveengine/exceptions.py
hiveengine/market.py
hiveengine/nft.py
hiveengine/nftmarket.py
hiveengine/nfts.py
hiveengine/rpc.py
hiveengine/tokenobject.py
hiveengine/tokens.py
hiveengine/version.py
hiveengine/wallet.py
hiveengine-0.2.2.dist-info/LICENSE
hiveengine-0.2.2.dist-info/METADATA
hiveengine-0.2.2.dist-info/WHEEL
hiveengine-0.2.2.dist-info/entry_points.txt
hiveengine-0.2.2.dist-info/top_level.txt
hiveengine-0.2.2.dist-info/RECORD
