Metadata-Version: 2.1
Name: hiveengine
Version: 0.2.2
Summary: command line tool and python library for sending hive engine tokens
Home-page: UNKNOWN
Author: Holger Nahrstaedt
Author-email: nahrstaedt@gmail.com
Maintainer: Holger Nahrstaedt
Maintainer-email: nahrstaedt@gmail.com
License: UNKNOWN
Keywords: hive,tools,nft
Platform: UNKNOWN
Classifier: License :: OSI Approved :: MIT License
Classifier: Operating System :: OS Independent
Classifier: Programming Language :: Python
Classifier: Programming Language :: Python :: 3
Classifier: Programming Language :: Python :: 3.5
Classifier: Programming Language :: Python :: 3.6
Classifier: Programming Language :: Python :: 3.7
Classifier: Programming Language :: Python :: 3.8
Classifier: Development Status :: 4 - Beta
Classifier: Intended Audience :: Developers
Requires-Dist: beem
Requires-Dist: requests
Requires-Dist: six
